[
    {
        "fields": {
            "cip_code": "0100",
            "cip_title": "Agriculture, General.",
            "college": 1,
            "created": "2021-01-03T10:13:06.644364-08:00",
            "credential_level": "Bachelor’s Degree",
            "credential_title": "Bachelors Degree",
            "debt_meam": null,
            "debt_median": null,
            "debt_monthly_payment": null,
            "debt_num_students": null,
            "earnings_1yr_median_earnings": null,
            "earnings_1yr_not_working_not_enrolled_num_students": null,
            "earnings_1yr_over_poverty_line_num_students": null,
            "earnings_1yr_working_not_enrolled_num_students": null,
            "earnings_2yr_median_earnings": null,
            "earnings_2yr_not_working_not_enrolled_num_students": null,
            "earnings_2yr_over_poverty_line_num_students": null,
            "earnings_2yr_working_not_enrolled_num_students": null,
            "ipeds_awards1_num_students": null,
            "ipeds_awards2_num_students": null,
            "plus_debt_mean": null,
            "plus_debt_median": null,
            "plus_debt_monthly_payment": null,
            "plus_debt_num_students": null,
            "scorecard": 1,
            "updated": "2021-01-03T10:13:06.644364-08:00"
        },
        "model": "colleges.FieldOfStudy",
        "pk": 1
    },
    {
        "fields": {
            "cip_code": "0109",
            "cip_title": "Animal Sciences.",
            "college": 1,
            "created": "2021-01-03T10:13:06.644364-08:00",
            "credential_level": "Bachelor’s Degree",
            "credential_title": "Bachelors Degree",
            "debt_meam": null,
            "debt_median": null,
            "debt_monthly_payment": null,
            "debt_num_students": null,
            "earnings_1yr_median_earnings": null,
            "earnings_1yr_not_working_not_enrolled_num_students": null,
            "earnings_1yr_over_poverty_line_num_students": null,
            "earnings_1yr_working_not_enrolled_num_students": null,
            "earnings_2yr_median_earnings": null,
            "earnings_2yr_not_working_not_enrolled_num_students": null,
            "earnings_2yr_over_poverty_line_num_students": null,
            "earnings_2yr_working_not_enrolled_num_students": null,
            "ipeds_awards1_num_students": 6,
            "ipeds_awards2_num_students": 5,
            "plus_debt_mean": null,
            "plus_debt_median": null,
            "plus_debt_monthly_payment": null,
            "plus_debt_num_students": null,
            "scorecard": 1,
            "updated": "2021-01-03T10:13:06.644364-08:00"
        },
        "model": "colleges.FieldOfStudy",
        "pk": 1
    },
    {
        "fields": {
            "cip_code": "0110",
            "cip_title": "Food Science and Technology.",
            "college": 1,
            "created": "2021-01-03T10:13:06.644364-08:00",
            "credential_level": "Bachelor’s Degree",
            "credential_title": "Bachelors Degree",
            "debt_meam": null,
            "debt_median": null,
            "debt_monthly_payment": null,
            "debt_num_students": 13,
            "earnings_1yr_median_earnings": null,
            "earnings_1yr_not_working_not_enrolled_num_students": null,
            "earnings_1yr_over_poverty_line_num_students": null,
            "earnings_1yr_working_not_enrolled_num_students": null,
            "earnings_2yr_median_earnings": null,
            "earnings_2yr_not_working_not_enrolled_num_students": null,
            "earnings_2yr_over_poverty_line_num_students": null,
            "earnings_2yr_working_not_enrolled_num_students": null,
            "ipeds_awards1_num_students": 8,
            "ipeds_awards2_num_students": 9,
            "plus_debt_mean": null,
            "plus_debt_median": null,
            "plus_debt_monthly_payment": null,
            "plus_debt_num_students": null,
            "scorecard": 1,
            "updated": "2021-01-03T10:13:06.644364-08:00"
        },
        "model": "colleges.FieldOfStudy",
        "pk": 1
    },
    {
        "fields": {
            "cip_code": "0110",
            "cip_title": "Food Science and Technology.",
            "college": 1,
            "created": "2021-01-03T10:13:06.644364-08:00",
            "credential_level": "Master's Degree",
            "credential_title": "Master's Degree",
            "debt_meam": null,
            "debt_median": null,
            "debt_monthly_payment": null,
            "debt_num_students": null,
            "earnings_1yr_median_earnings": 52107,
            "earnings_1yr_not_working_not_enrolled_num_students": 1,
            "earnings_1yr_over_poverty_line_num_students": 13,
            "earnings_1yr_working_not_enrolled_num_students": 13,
            "earnings_2yr_median_earnings": null,
            "earnings_2yr_not_working_not_enrolled_num_students": null,
            "earnings_2yr_over_poverty_line_num_students": null,
            "earnings_2yr_working_not_enrolled_num_students": null,
            "ipeds_awards1_num_students": 10,
            "ipeds_awards2_num_students": 5,
            "plus_debt_mean": null,
            "plus_debt_median": null,
            "plus_debt_monthly_payment": null,
            "plus_debt_num_students": null,
            "scorecard": 1,
            "updated": "2021-01-03T10:13:06.644364-08:00"
        },
        "model": "colleges.FieldOfStudy",
        "pk": 1
    },
    {
        "fields": {
            "cip_code": "0110",
            "cip_title": "Food Science and Technology.",
            "college": 1,
            "created": "2021-01-03T10:13:06.644364-08:00",
            "credential_level": "Doctoral Degree",
            "credential_title": "Doctoral Degree",
            "debt_meam": null,
            "debt_median": null,
            "debt_monthly_payment": null,
            "debt_num_students": null,
            "earnings_1yr_median_earnings": null,
            "earnings_1yr_not_working_not_enrolled_num_students": null,
            "earnings_1yr_over_poverty_line_num_students": null,
            "earnings_1yr_working_not_enrolled_num_students": null,
            "earnings_2yr_median_earnings": null,
            "earnings_2yr_not_working_not_enrolled_num_students": null,
            "earnings_2yr_over_poverty_line_num_students": null,
            "earnings_2yr_working_not_enrolled_num_students": null,
            "ipeds_awards1_num_students": 4,
            "ipeds_awards2_num_students": 1,
            "plus_debt_mean": null,
            "plus_debt_median": null,
            "plus_debt_monthly_payment": null,
            "plus_debt_num_students": null,
            "scorecard": 1,
            "updated": "2021-01-03T10:13:06.644364-08:00"
        },
        "model": "colleges.FieldOfStudy",
        "pk": 1
    },
    {
        "fields": {
            "cip_code": "0111",
            "cip_title": "Plant Sciences.",
            "college": 1,
            "created": "2021-01-03T10:13:06.644364-08:00",
            "credential_level": "Bachelor’s Degree",
            "credential_title": "Bachelors Degree",
            "debt_meam": null,
            "debt_median": null,
            "debt_monthly_payment": null,
            "debt_num_students": null,
            "earnings_1yr_median_earnings": null,
            "earnings_1yr_not_working_not_enrolled_num_students": null,
            "earnings_1yr_over_poverty_line_num_students": null,
            "earnings_1yr_working_not_enrolled_num_students": null,
            "earnings_2yr_median_earnings": null,
            "earnings_2yr_not_working_not_enrolled_num_students": null,
            "earnings_2yr_over_poverty_line_num_students": null,
            "earnings_2yr_working_not_enrolled_num_students": null,
            "ipeds_awards1_num_students": null,
            "ipeds_awards2_num_students": null,
            "plus_debt_mean": null,
            "plus_debt_median": null,
            "plus_debt_monthly_payment": null,
            "plus_debt_num_students": null,
            "scorecard": 1,
            "updated": "2021-01-03T10:13:06.644364-08:00"
        },
        "model": "colleges.FieldOfStudy",
        "pk": 1
    },
    {
        "fields": {
            "cip_code": "0199",
            "cip_title": "Agriculture, Agriculture Operations, and Related Sciences, Other.",
            "college": 1,
            "created": "2021-01-03T10:13:06.644364-08:00",
            "credential_level": "Bachelor’s Degree",
            "credential_title": "Bachelors Degree",
            "debt_meam": null,
            "debt_median": null,
            "debt_monthly_payment": null,
            "debt_num_students": null,
            "earnings_1yr_median_earnings": null,
            "earnings_1yr_not_working_not_enrolled_num_students": null,
            "earnings_1yr_over_poverty_line_num_students": null,
            "earnings_1yr_working_not_enrolled_num_students": null,
            "earnings_2yr_median_earnings": null,
            "earnings_2yr_not_working_not_enrolled_num_students": null,
            "earnings_2yr_over_poverty_line_num_students": null,
            "earnings_2yr_working_not_enrolled_num_students": null,
            "ipeds_awards1_num_students": 3,
            "ipeds_awards2_num_students": 6,
            "plus_debt_mean": null,
            "plus_debt_median": null,
            "plus_debt_monthly_payment": null,
            "plus_debt_num_students": null,
            "scorecard": 1,
            "updated": "2021-01-03T10:13:06.644364-08:00"
        },
        "model": "colleges.FieldOfStudy",
        "pk": 1
    },
    {
        "fields": {
            "cip_code": "0199",
            "cip_title": "Agriculture, Agriculture Operations, and Related Sciences, Other.",
            "college": 1,
            "created": "2021-01-03T10:13:06.644364-08:00",
            "credential_level": "Master's Degree",
            "credential_title": "Master's Degree",
            "debt_meam": null,
            "debt_median": null,
            "debt_monthly_payment": null,
            "debt_num_students": null,
            "earnings_1yr_median_earnings": null,
            "earnings_1yr_not_working_not_enrolled_num_students": null,
            "earnings_1yr_over_poverty_line_num_students": null,
            "earnings_1yr_working_not_enrolled_num_students": null,
            "earnings_2yr_median_earnings": null,
            "earnings_2yr_not_working_not_enrolled_num_students": null,
            "earnings_2yr_over_poverty_line_num_students": null,
            "earnings_2yr_working_not_enrolled_num_students": null,
            "ipeds_awards1_num_students": 8,
            "ipeds_awards2_num_students": 7,
            "plus_debt_mean": null,
            "plus_debt_median": null,
            "plus_debt_monthly_payment": null,
            "plus_debt_num_students": null,
            "scorecard": 1,
            "updated": "2021-01-03T10:13:06.644364-08:00"
        },
        "model": "colleges.FieldOfStudy",
        "pk": 1
    },
    {
        "fields": {
            "cip_code": "0199",
            "cip_title": "Agriculture, Agriculture Operations, and Related Sciences, Other.",
            "college": 1,
            "created": "2021-01-03T10:13:06.644364-08:00",
            "credential_level": "Doctoral Degree",
            "credential_title": "Doctoral Degree",
            "debt_meam": null,
            "debt_median": null,
            "debt_monthly_payment": null,
            "debt_num_students": null,
            "earnings_1yr_median_earnings": null,
            "earnings_1yr_not_working_not_enrolled_num_students": null,
            "earnings_1yr_over_poverty_line_num_students": null,
            "earnings_1yr_working_not_enrolled_num_students": null,
            "earnings_2yr_median_earnings": null,
            "earnings_2yr_not_working_not_enrolled_num_students": null,
            "earnings_2yr_over_poverty_line_num_students": null,
            "earnings_2yr_working_not_enrolled_num_students": null,
            "ipeds_awards1_num_students": 2,
            "ipeds_awards2_num_students": 1,
            "plus_debt_mean": null,
            "plus_debt_median": null,
            "plus_debt_monthly_payment": null,
            "plus_debt_num_students": null,
            "scorecard": 1,
            "updated": "2021-01-03T10:13:06.644364-08:00"
        },
        "model": "colleges.FieldOfStudy",
        "pk": 1
    },
    {
        "fields": {
            "cip_code": "0305",
            "cip_title": "Forestry.",
            "college": 1,
            "created": "2021-01-03T10:13:06.644364-08:00",
            "credential_level": "Bachelor’s Degree",
            "credential_title": "Bachelors Degree",
            "debt_meam": null,
            "debt_median": null,
            "debt_monthly_payment": null,
            "debt_num_students": null,
            "earnings_1yr_median_earnings": null,
            "earnings_1yr_not_working_not_enrolled_num_students": null,
            "earnings_1yr_over_poverty_line_num_students": null,
            "earnings_1yr_working_not_enrolled_num_students": null,
            "earnings_2yr_median_earnings": null,
            "earnings_2yr_not_working_not_enrolled_num_students": null,
            "earnings_2yr_over_poverty_line_num_students": null,
            "earnings_2yr_working_not_enrolled_num_students": null,
            "ipeds_awards1_num_students": 8,
            "ipeds_awards2_num_students": 12,
            "plus_debt_mean": null,
            "plus_debt_median": null,
            "plus_debt_monthly_payment": null,
            "plus_debt_num_students": null,
            "scorecard": 1,
            "updated": "2021-01-03T10:13:06.644364-08:00"
        },
        "model": "colleges.FieldOfStudy",
        "pk": 1
    },
    {
        "fields": {
            "cip_code": "0403",
            "cip_title": "City/Urban, Community and Regional Planning.",
            "college": 1,
            "created": "2021-01-03T10:13:06.644364-08:00",
            "credential_level": "Bachelor’s Degree",
            "credential_title": "Bachelors Degree",
            "debt_meam": null,
            "debt_median": null,
            "debt_monthly_payment": null,
            "debt_num_students": null,
            "earnings_1yr_median_earnings": null,
            "earnings_1yr_not_working_not_enrolled_num_students": null,
            "earnings_1yr_over_poverty_line_num_students": null,
            "earnings_1yr_working_not_enrolled_num_students": null,
            "earnings_2yr_median_earnings": null,
            "earnings_2yr_not_working_not_enrolled_num_students": null,
            "earnings_2yr_over_poverty_line_num_students": null,
            "earnings_2yr_working_not_enrolled_num_students": null,
            "ipeds_awards1_num_students": 4,
            "ipeds_awards2_num_students": 2,
            "plus_debt_mean": null,
            "plus_debt_median": null,
            "plus_debt_monthly_payment": null,
            "plus_debt_num_students": null,
            "scorecard": 1,
            "updated": "2021-01-03T10:13:06.644364-08:00"
        },
        "model": "colleges.FieldOfStudy",
        "pk": 1
    },
    {
        "fields": {
            "cip_code": "0403",
            "cip_title": "City/Urban, Community and Regional Planning.",
            "college": 1,
            "created": "2021-01-03T10:13:06.644364-08:00",
            "credential_level": "Master's Degree",
            "credential_title": "Master's Degree",
            "debt_meam": null,
            "debt_median": null,
            "debt_monthly_payment": null,
            "debt_num_students": null,
            "earnings_1yr_median_earnings": null,
            "earnings_1yr_not_working_not_enrolled_num_students": null,
            "earnings_1yr_over_poverty_line_num_students": null,
            "earnings_1yr_working_not_enrolled_num_students": null,
            "earnings_2yr_median_earnings": 47260,
            "earnings_2yr_not_working_not_enrolled_num_students": 0,
            "earnings_2yr_over_poverty_line_num_students": 12,
            "earnings_2yr_working_not_enrolled_num_students": 12,
            "ipeds_awards1_num_students": 7,
            "ipeds_awards2_num_students": 11,
            "plus_debt_mean": null,
            "plus_debt_median": null,
            "plus_debt_monthly_payment": null,
            "plus_debt_num_students": null,
            "scorecard": 1,
            "updated": "2021-01-03T10:13:06.644364-08:00"
        },
        "model": "colleges.FieldOfStudy",
        "pk": 1
    },
    {
        "fields": {
            "cip_code": "0901",
            "cip_title": "Communication and Media Studies.",
            "college": 1,
            "created": "2021-01-03T10:13:06.644364-08:00",
            "credential_level": "Master's Degree",
            "credential_title": "Master's Degree",
            "debt_meam": null,
            "debt_median": null,
            "debt_monthly_payment": null,
            "debt_num_students": null,
            "earnings_1yr_median_earnings": null,
            "earnings_1yr_not_working_not_enrolled_num_students": null,
            "earnings_1yr_over_poverty_line_num_students": null,
            "earnings_1yr_working_not_enrolled_num_students": null,
            "earnings_2yr_median_earnings": null,
            "earnings_2yr_not_working_not_enrolled_num_students": null,
            "earnings_2yr_over_poverty_line_num_students": null,
            "earnings_2yr_working_not_enrolled_num_students": null,
            "ipeds_awards1_num_students": 8,
            "ipeds_awards2_num_students": 17,
            "plus_debt_mean": null,
            "plus_debt_median": null,
            "plus_debt_monthly_payment": null,
            "plus_debt_num_students": null,
            "scorecard": 1,
            "updated": "2021-01-03T10:13:06.644364-08:00"
        },
        "model": "colleges.FieldOfStudy",
        "pk": 1
    },
    {
        "fields": {
            "cip_code": "1002",
            "cip_title": "Audiovisual Communications Technologies/Technicians.",
            "college": 1,
            "created": "2021-01-03T10:13:06.644364-08:00",
            "credential_level": "Bachelor’s Degree",
            "credential_title": "Bachelors Degree",
            "debt_meam": null,
            "debt_median": 31250,
            "debt_monthly_payment": 298,
            "debt_num_students": 34,
            "earnings_1yr_median_earnings": 25194,
            "earnings_1yr_not_working_not_enrolled_num_students": 0,
            "earnings_1yr_over_poverty_line_num_students": 11,
            "earnings_1yr_working_not_enrolled_num_students": 17,
            "earnings_2yr_median_earnings": 20102,
            "earnings_2yr_not_working_not_enrolled_num_students": 0,
            "earnings_2yr_over_poverty_line_num_students": 6,
            "earnings_2yr_working_not_enrolled_num_students": 12,
            "ipeds_awards1_num_students": 20,
            "ipeds_awards2_num_students": 20,
            "plus_debt_mean": null,
            "plus_debt_median": null,
            "plus_debt_monthly_payment": null,
            "plus_debt_num_students": 16,
            "scorecard": 1,
            "updated": "2021-01-03T10:13:06.644364-08:00"
        },
        "model": "colleges.FieldOfStudy",
        "pk": 1
    },
    {
        "fields": {
            "cip_code": "1101",
            "cip_title": "Computer and Information Sciences, General.",
            "college": 1,
            "created": "2021-01-03T10:13:06.644364-08:00",
            "credential_level": "Bachelor’s Degree",
            "credential_title": "Bachelors Degree",
            "debt_meam": 34700,
            "debt_median": 35000,
            "debt_monthly_payment": 334,
            "debt_num_students": 36,
            "earnings_1yr_median_earnings": 67101,
            "earnings_1yr_not_working_not_enrolled_num_students": 1,
            "earnings_1yr_over_poverty_line_num_students": 21,
            "earnings_1yr_working_not_enrolled_num_students": 22,
            "earnings_2yr_median_earnings": 52107,
            "earnings_2yr_not_working_not_enrolled_num_students": 0,
            "earnings_2yr_over_poverty_line_num_students": 29,
            "earnings_2yr_working_not_enrolled_num_students": 31,
            "ipeds_awards1_num_students": 16,
            "ipeds_awards2_num_students": 30,
            "plus_debt_mean": null,
            "plus_debt_median": null,
            "plus_debt_monthly_payment": null,
            "plus_debt_num_students": 15,
            "scorecard": 1,
            "updated": "2021-01-03T10:13:06.644364-08:00"
        },
        "model": "colleges.FieldOfStudy",
        "pk": 1
    },
    {
        "fields": {
            "cip_code": "1101",
            "cip_title": "Computer and Information Sciences, General.",
            "college": 1,
            "created": "2021-01-03T10:13:06.644364-08:00",
            "credential_level": "Master's Degree",
            "credential_title": "Master's Degree",
            "debt_meam": null,
            "debt_median": null,
            "debt_monthly_payment": null,
            "debt_num_students": null,
            "earnings_1yr_median_earnings": 47666,
            "earnings_1yr_not_working_not_enrolled_num_students": 1,
            "earnings_1yr_over_poverty_line_num_students": 10,
            "earnings_1yr_working_not_enrolled_num_students": 13,
            "earnings_2yr_median_earnings": null,
            "earnings_2yr_not_working_not_enrolled_num_students": null,
            "earnings_2yr_over_poverty_line_num_students": null,
            "earnings_2yr_working_not_enrolled_num_students": null,
            "ipeds_awards1_num_students": 15,
            "ipeds_awards2_num_students": 9,
            "plus_debt_mean": null,
            "plus_debt_median": null,
            "plus_debt_monthly_payment": null,
            "plus_debt_num_students": null,
            "scorecard": 1,
            "updated": "2021-01-03T10:13:06.644364-08:00"
        },
        "model": "colleges.FieldOfStudy",
        "pk": 1
    },
    {
        "fields": {
            "cip_code": "1301",
            "cip_title": "Education, General.",
            "college": 1,
            "created": "2021-01-03T10:13:06.644364-08:00",
            "credential_level": "Master's Degree",
            "credential_title": "Master's Degree",
            "debt_meam": null,
            "debt_median": null,
            "debt_monthly_payment": null,
            "debt_num_students": null,
            "earnings_1yr_median_earnings": null,
            "earnings_1yr_not_working_not_enrolled_num_students": null,
            "earnings_1yr_over_poverty_line_num_students": null,
            "earnings_1yr_working_not_enrolled_num_students": null,
            "earnings_2yr_median_earnings": null,
            "earnings_2yr_not_working_not_enrolled_num_students": null,
            "earnings_2yr_over_poverty_line_num_students": null,
            "earnings_2yr_working_not_enrolled_num_students": null,
            "ipeds_awards1_num_students": null,
            "ipeds_awards2_num_students": null,
            "plus_debt_mean": null,
            "plus_debt_median": null,
            "plus_debt_monthly_payment": null,
            "plus_debt_num_students": null,
            "scorecard": 1,
            "updated": "2021-01-03T10:13:06.644364-08:00"
        },
        "model": "colleges.FieldOfStudy",
        "pk": 1
    },
    {
        "fields": {
            "cip_code": "1301",
            "cip_title": "Education, General.",
            "college": 1,
            "created": "2021-01-03T10:13:06.644364-08:00",
            "credential_level": "Graduate/Professional Certificate",
            "credential_title": "Graduate/Professional Certificate",
            "debt_meam": null,
            "debt_median": null,
            "debt_monthly_payment": null,
            "debt_num_students": null,
            "earnings_1yr_median_earnings": null,
            "earnings_1yr_not_working_not_enrolled_num_students": null,
            "earnings_1yr_over_poverty_line_num_students": null,
            "earnings_1yr_working_not_enrolled_num_students": null,
            "earnings_2yr_median_earnings": null,
            "earnings_2yr_not_working_not_enrolled_num_students": null,
            "earnings_2yr_over_poverty_line_num_students": null,
            "earnings_2yr_working_not_enrolled_num_students": null,
            "ipeds_awards1_num_students": 2,
            "ipeds_awards2_num_students": null,
            "plus_debt_mean": null,
            "plus_debt_median": null,
            "plus_debt_monthly_payment": null,
            "plus_debt_num_students": null,
            "scorecard": 1,
            "updated": "2021-01-03T10:13:06.644364-08:00"
        },
        "model": "colleges.FieldOfStudy",
        "pk": 1
    },
    {
        "fields": {
            "cip_code": "1304",
            "cip_title": "Educational Administration and Supervision.",
            "college": 1,
            "created": "2021-01-03T10:13:06.644364-08:00",
            "credential_level": "Master's Degree",
            "credential_title": "Master's Degree",
            "debt_meam": null,
            "debt_median": null,
            "debt_monthly_payment": null,
            "debt_num_students": null,
            "earnings_1yr_median_earnings": 52941,
            "earnings_1yr_not_working_not_enrolled_num_students": 2,
            "earnings_1yr_over_poverty_line_num_students": 15,
            "earnings_1yr_working_not_enrolled_num_students": 16,
            "earnings_2yr_median_earnings": 50231,
            "earnings_2yr_not_working_not_enrolled_num_students": 0,
            "earnings_2yr_over_poverty_line_num_students": 8,
            "earnings_2yr_working_not_enrolled_num_students": 11,
            "ipeds_awards1_num_students": 14,
            "ipeds_awards2_num_students": 4,
            "plus_debt_mean": null,
            "plus_debt_median": null,
            "plus_debt_monthly_payment": null,
            "plus_debt_num_students": null,
            "scorecard": 1,
            "updated": "2021-01-03T10:13:06.644364-08:00"
        },
        "model": "colleges.FieldOfStudy",
        "pk": 1
    },
    {
        "fields": {
            "cip_code": "1310",
            "cip_title": "Special Education and Teaching.",
            "college": 1,
            "created": "2021-01-03T10:13:06.644364-08:00",
            "credential_level": "Bachelor’s Degree",
            "credential_title": "Bachelors Degree",
            "debt_meam": null,
            "debt_median": null,
            "debt_monthly_payment": null,
            "debt_num_students": 12,
            "earnings_1yr_median_earnings": null,
            "earnings_1yr_not_working_not_enrolled_num_students": null,
            "earnings_1yr_over_poverty_line_num_students": null,
            "earnings_1yr_working_not_enrolled_num_students": null,
            "earnings_2yr_median_earnings": null,
            "earnings_2yr_not_working_not_enrolled_num_students": null,
            "earnings_2yr_over_poverty_line_num_students": null,
            "earnings_2yr_working_not_enrolled_num_students": null,
            "ipeds_awards1_num_students": 10,
            "ipeds_awards2_num_students": 10,
            "plus_debt_mean": null,
            "plus_debt_median": null,
            "plus_debt_monthly_payment": null,
            "plus_debt_num_students": null,
            "scorecard": 1,
            "updated": "2021-01-03T10:13:06.644364-08:00"
        },
        "model": "colleges.FieldOfStudy",
        "pk": 1
    },
    {
        "fields": {
            "cip_code": "1310",
            "cip_title": "Special Education and Teaching.",
            "college": 1,
            "created": "2021-01-03T10:13:06.644364-08:00",
            "credential_level": "Master's Degree",
            "credential_title": "Master's Degree",
            "debt_meam": null,
            "debt_median": null,
            "debt_monthly_payment": null,
            "debt_num_students": null,
            "earnings_1yr_median_earnings": null,
            "earnings_1yr_not_working_not_enrolled_num_students": null,
            "earnings_1yr_over_poverty_line_num_students": null,
            "earnings_1yr_working_not_enrolled_num_students": null,
            "earnings_2yr_median_earnings": null,
            "earnings_2yr_not_working_not_enrolled_num_students": null,
            "earnings_2yr_over_poverty_line_num_students": null,
            "earnings_2yr_working_not_enrolled_num_students": null,
            "ipeds_awards1_num_students": 2,
            "ipeds_awards2_num_students": 3,
            "plus_debt_mean": null,
            "plus_debt_median": null,
            "plus_debt_monthly_payment": null,
            "plus_debt_num_students": null,
            "scorecard": 1,
            "updated": "2021-01-03T10:13:06.644364-08:00"
        },
        "model": "colleges.FieldOfStudy",
        "pk": 1
    },
    {
        "fields": {
            "cip_code": "1312",
            "cip_title": "Teacher Education and Professional Development, Specific Levels and Methods.",
            "college": 1,
            "created": "2021-01-03T10:13:06.644364-08:00",
            "credential_level": "Bachelor’s Degree",
            "credential_title": "Bachelors Degree",
            "debt_meam": null,
            "debt_median": null,
            "debt_monthly_payment": null,
            "debt_num_students": null,
            "earnings_1yr_median_earnings": 37208,
            "earnings_1yr_not_working_not_enrolled_num_students": 0,
            "earnings_1yr_over_poverty_line_num_students": 12,
            "earnings_1yr_working_not_enrolled_num_students": 13,
            "earnings_2yr_median_earnings": 37208,
            "earnings_2yr_not_working_not_enrolled_num_students": 0,
            "earnings_2yr_over_poverty_line_num_students": 14,
            "earnings_2yr_working_not_enrolled_num_students": 15,
            "ipeds_awards1_num_students": 11,
            "ipeds_awards2_num_students": 8,
            "plus_debt_mean": null,
            "plus_debt_median": null,
            "plus_debt_monthly_payment": null,
            "plus_debt_num_students": null,
            "scorecard": 1,
            "updated": "2021-01-03T10:13:06.644364-08:00"
        },
        "model": "colleges.FieldOfStudy",
        "pk": 1
    },
    {
        "fields": {
            "cip_code": "1312",
            "cip_title": "Teacher Education and Professional Development, Specific Levels and Methods.",
            "college": 1,
            "created": "2021-01-03T10:13:06.644364-08:00",
            "credential_level": "Master's Degree",
            "credential_title": "Master's Degree",
            "debt_meam": null,
            "debt_median": null,
            "debt_monthly_payment": null,
            "debt_num_students": null,
            "earnings_1yr_median_earnings": 45940,
            "earnings_1yr_not_working_not_enrolled_num_students": 0,
            "earnings_1yr_over_poverty_line_num_students": 40,
            "earnings_1yr_working_not_enrolled_num_students": 39,
            "earnings_2yr_median_earnings": 43240,
            "earnings_2yr_not_working_not_enrolled_num_students": 0,
            "earnings_2yr_over_poverty_line_num_students": 18,
            "earnings_2yr_working_not_enrolled_num_students": 19,
            "ipeds_awards1_num_students": 28,
            "ipeds_awards2_num_students": 24,
            "plus_debt_mean": null,
            "plus_debt_median": null,
            "plus_debt_monthly_payment": null,
            "plus_debt_num_students": null,
            "scorecard": 1,
            "updated": "2021-01-03T10:13:06.644364-08:00"
        },
        "model": "colleges.FieldOfStudy",
        "pk": 1
    },
    {
        "fields": {
            "cip_code": "1313",
            "cip_title": "Teacher Education and Professional Development, Specific Subject Areas.",
            "college": 1,
            "created": "2021-01-03T10:13:06.644364-08:00",
            "credential_level": "Bachelor’s Degree",
            "credential_title": "Bachelors Degree",
            "debt_meam": null,
            "debt_median": 42000,
            "debt_monthly_payment": 401,
            "debt_num_students": 44,
            "earnings_1yr_median_earnings": 28816,
            "earnings_1yr_not_working_not_enrolled_num_students": 1,
            "earnings_1yr_over_poverty_line_num_students": 27,
            "earnings_1yr_working_not_enrolled_num_students": 33,
            "earnings_2yr_median_earnings": 27497,
            "earnings_2yr_not_working_not_enrolled_num_students": 1,
            "earnings_2yr_over_poverty_line_num_students": 23,
            "earnings_2yr_working_not_enrolled_num_students": 30,
            "ipeds_awards1_num_students": 33,
            "ipeds_awards2_num_students": 18,
            "plus_debt_mean": null,
            "plus_debt_median": null,
            "plus_debt_monthly_payment": null,
            "plus_debt_num_students": 18,
            "scorecard": 1,
            "updated": "2021-01-03T10:13:06.644364-08:00"
        },
        "model": "colleges.FieldOfStudy",
        "pk": 1
    },
    {
        "fields": {
            "cip_code": "1313",
            "cip_title": "Teacher Education and Professional Development, Specific Subject Areas.",
            "college": 1,
            "created": "2021-01-03T10:13:06.644364-08:00",
            "credential_level": "Master's Degree",
            "credential_title": "Master's Degree",
            "debt_meam": null,
            "debt_median": null,
            "debt_monthly_payment": null,
            "debt_num_students": null,
            "earnings_1yr_median_earnings": null,
            "earnings_1yr_not_working_not_enrolled_num_students": null,
            "earnings_1yr_over_poverty_line_num_students": null,
            "earnings_1yr_working_not_enrolled_num_students": null,
            "earnings_2yr_median_earnings": null,
            "earnings_2yr_not_working_not_enrolled_num_students": null,
            "earnings_2yr_over_poverty_line_num_students": null,
            "earnings_2yr_working_not_enrolled_num_students": null,
            "ipeds_awards1_num_students": null,
            "ipeds_awards2_num_students": null,
            "plus_debt_mean": null,
            "plus_debt_median": null,
            "plus_debt_monthly_payment": null,
            "plus_debt_num_students": null,
            "scorecard": 1,
            "updated": "2021-01-03T10:13:06.644364-08:00"
        },
        "model": "colleges.FieldOfStudy",
        "pk": 1
    },
    {
        "fields": {
            "cip_code": "1313",
            "cip_title": "Teacher Education and Professional Development, Specific Subject Areas.",
            "college": 1,
            "created": "2021-01-03T10:13:06.644364-08:00",
            "credential_level": "Doctoral Degree",
            "credential_title": "Doctoral Degree",
            "debt_meam": null,
            "debt_median": null,
            "debt_monthly_payment": null,
            "debt_num_students": null,
            "earnings_1yr_median_earnings": null,
            "earnings_1yr_not_working_not_enrolled_num_students": null,
            "earnings_1yr_over_poverty_line_num_students": null,
            "earnings_1yr_working_not_enrolled_num_students": null,
            "earnings_2yr_median_earnings": null,
            "earnings_2yr_not_working_not_enrolled_num_students": null,
            "earnings_2yr_over_poverty_line_num_students": null,
            "earnings_2yr_working_not_enrolled_num_students": null,
            "ipeds_awards1_num_students": null,
            "ipeds_awards2_num_students": 6,
            "plus_debt_mean": null,
            "plus_debt_median": null,
            "plus_debt_monthly_payment": null,
            "plus_debt_num_students": null,
            "scorecard": 1,
            "updated": "2021-01-03T10:13:06.644364-08:00"
        },
        "model": "colleges.FieldOfStudy",
        "pk": 1
    },
    {
        "fields": {
            "cip_code": "1408",
            "cip_title": "Civil Engineering.",
            "college": 1,
            "created": "2021-01-03T10:13:06.644364-08:00",
            "credential_level": "Bachelor’s Degree",
            "credential_title": "Bachelors Degree",
            "debt_meam": null,
            "debt_median": null,
            "debt_monthly_payment": null,
            "debt_num_students": null,
            "earnings_1yr_median_earnings": 47260,
            "earnings_1yr_not_working_not_enrolled_num_students": 0,
            "earnings_1yr_over_poverty_line_num_students": 11,
            "earnings_1yr_working_not_enrolled_num_students": 11,
            "earnings_2yr_median_earnings": 47260,
            "earnings_2yr_not_working_not_enrolled_num_students": 0,
            "earnings_2yr_over_poverty_line_num_students": 12,
            "earnings_2yr_working_not_enrolled_num_students": 12,
            "ipeds_awards1_num_students": 6,
            "ipeds_awards2_num_students": 5,
            "plus_debt_mean": null,
            "plus_debt_median": null,
            "plus_debt_monthly_payment": null,
            "plus_debt_num_students": null,
            "scorecard": 1,
            "updated": "2021-01-03T10:13:06.644364-08:00"
        },
        "model": "colleges.FieldOfStudy",
        "pk": 1
    },
    {
        "fields": {
            "cip_code": "1410",
            "cip_title": "Electrical, Electronics and Communications Engineering.",
            "college": 1,
            "created": "2021-01-03T10:13:06.644364-08:00",
            "credential_level": "Bachelor’s Degree",
            "credential_title": "Bachelors Degree",
            "debt_meam": null,
            "debt_median": 33000,
            "debt_monthly_payment": 315,
            "debt_num_students": 30,
            "earnings_1yr_median_earnings": 69338,
            "earnings_1yr_not_working_not_enrolled_num_students": 1,
            "earnings_1yr_over_poverty_line_num_students": 15,
            "earnings_1yr_working_not_enrolled_num_students": 17,
            "earnings_2yr_median_earnings": 61303,
            "earnings_2yr_not_working_not_enrolled_num_students": 2,
            "earnings_2yr_over_poverty_line_num_students": 28,
            "earnings_2yr_working_not_enrolled_num_students": 29,
            "ipeds_awards1_num_students": 11,
            "ipeds_awards2_num_students": 28,
            "plus_debt_mean": null,
            "plus_debt_median": null,
            "plus_debt_monthly_payment": null,
            "plus_debt_num_students": 12,
            "scorecard": 1,
            "updated": "2021-01-03T10:13:06.644364-08:00"
        },
        "model": "colleges.FieldOfStudy",
        "pk": 1
    },
    {
        "fields": {
            "cip_code": "1419",
            "cip_title": "Mechanical Engineering.",
            "college": 1,
            "created": "2021-01-03T10:13:06.644364-08:00",
            "credential_level": "Bachelor’s Degree",
            "credential_title": "Bachelors Degree",
            "debt_meam": null,
            "debt_median": 36900,
            "debt_monthly_payment": 352,
            "debt_num_students": 38,
            "earnings_1yr_median_earnings": 53358,
            "earnings_1yr_not_working_not_enrolled_num_students": 0,
            "earnings_1yr_over_poverty_line_num_students": 26,
            "earnings_1yr_working_not_enrolled_num_students": 28,
            "earnings_2yr_median_earnings": 52107,
            "earnings_2yr_not_working_not_enrolled_num_students": 0,
            "earnings_2yr_over_poverty_line_num_students": 19,
            "earnings_2yr_working_not_enrolled_num_students": 23,
            "ipeds_awards1_num_students": 17,
            "ipeds_awards2_num_students": 27,
            "plus_debt_mean": null,
            "plus_debt_median": null,
            "plus_debt_monthly_payment": null,
            "plus_debt_num_students": 13,
            "scorecard": 1,
            "updated": "2021-01-03T10:13:06.644364-08:00"
        },
        "model": "colleges.FieldOfStudy",
        "pk": 1
    },
    {
        "fields": {
            "cip_code": "1499",
            "cip_title": "Engineering, Other.",
            "college": 1,
            "created": "2021-01-03T10:13:06.644364-08:00",
            "credential_level": "Master's Degree",
            "credential_title": "Master's Degree",
            "debt_meam": null,
            "debt_median": null,
            "debt_monthly_payment": null,
            "debt_num_students": null,
            "earnings_1yr_median_earnings": null,
            "earnings_1yr_not_working_not_enrolled_num_students": null,
            "earnings_1yr_over_poverty_line_num_students": null,
            "earnings_1yr_working_not_enrolled_num_students": null,
            "earnings_2yr_median_earnings": null,
            "earnings_2yr_not_working_not_enrolled_num_students": null,
            "earnings_2yr_over_poverty_line_num_students": null,
            "earnings_2yr_working_not_enrolled_num_students": null,
            "ipeds_awards1_num_students": 9,
            "ipeds_awards2_num_students": 17,
            "plus_debt_mean": null,
            "plus_debt_median": null,
            "plus_debt_monthly_payment": null,
            "plus_debt_num_students": null,
            "scorecard": 1,
            "updated": "2021-01-03T10:13:06.644364-08:00"
        },
        "model": "colleges.FieldOfStudy",
        "pk": 1
    },
    {
        "fields": {
            "cip_code": "1503",
            "cip_title": "Electrical Engineering Technologies/Technicians.",
            "college": 1,
            "created": "2021-01-03T10:13:06.644364-08:00",
            "credential_level": "Bachelor’s Degree",
            "credential_title": "Bachelors Degree",
            "debt_meam": null,
            "debt_median": null,
            "debt_monthly_payment": null,
            "debt_num_students": null,
            "earnings_1yr_median_earnings": null,
            "earnings_1yr_not_working_not_enrolled_num_students": null,
            "earnings_1yr_over_poverty_line_num_students": null,
            "earnings_1yr_working_not_enrolled_num_students": null,
            "earnings_2yr_median_earnings": null,
            "earnings_2yr_not_working_not_enrolled_num_students": null,
            "earnings_2yr_over_poverty_line_num_students": null,
            "earnings_2yr_working_not_enrolled_num_students": null,
            "ipeds_awards1_num_students": null,
            "ipeds_awards2_num_students": null,
            "plus_debt_mean": null,
            "plus_debt_median": null,
            "plus_debt_monthly_payment": null,
            "plus_debt_num_students": null,
            "scorecard": 1,
            "updated": "2021-01-03T10:13:06.644364-08:00"
        },
        "model": "colleges.FieldOfStudy",
        "pk": 1
    },
    {
        "fields": {
            "cip_code": "1508",
            "cip_title": "Mechanical Engineering Related Technologies/Technicians.",
            "college": 1,
            "created": "2021-01-03T10:13:06.644364-08:00",
            "credential_level": "Bachelor’s Degree",
            "credential_title": "Bachelors Degree",
            "debt_meam": null,
            "debt_median": null,
            "debt_monthly_payment": null,
            "debt_num_students": null,
            "earnings_1yr_median_earnings": null,
            "earnings_1yr_not_working_not_enrolled_num_students": null,
            "earnings_1yr_over_poverty_line_num_students": null,
            "earnings_1yr_working_not_enrolled_num_students": null,
            "earnings_2yr_median_earnings": 44971,
            "earnings_2yr_not_working_not_enrolled_num_students": 0,
            "earnings_2yr_over_poverty_line_num_students": 12,
            "earnings_2yr_working_not_enrolled_num_students": 13,
            "ipeds_awards1_num_students": 1,
            "ipeds_awards2_num_students": null,
            "plus_debt_mean": null,
            "plus_debt_median": null,
            "plus_debt_monthly_payment": null,
            "plus_debt_num_students": null,
            "scorecard": 1,
            "updated": "2021-01-03T10:13:06.644364-08:00"
        },
        "model": "colleges.FieldOfStudy",
        "pk": 1
    },
    {
        "fields": {
            "cip_code": "1510",
            "cip_title": "Construction Engineering Technologies.",
            "college": 1,
            "created": "2021-01-03T10:13:06.644364-08:00",
            "credential_level": "Bachelor’s Degree",
            "credential_title": "Bachelors Degree",
            "debt_meam": null,
            "debt_median": null,
            "debt_monthly_payment": null,
            "debt_num_students": null,
            "earnings_1yr_median_earnings": 50465,
            "earnings_1yr_not_working_not_enrolled_num_students": 0,
            "earnings_1yr_over_poverty_line_num_students": 14,
            "earnings_1yr_working_not_enrolled_num_students": 15,
            "earnings_2yr_median_earnings": null,
            "earnings_2yr_not_working_not_enrolled_num_students": null,
            "earnings_2yr_over_poverty_line_num_students": null,
            "earnings_2yr_working_not_enrolled_num_students": null,
            "ipeds_awards1_num_students": 12,
            "ipeds_awards2_num_students": 10,
            "plus_debt_mean": null,
            "plus_debt_median": null,
            "plus_debt_monthly_payment": null,
            "plus_debt_num_students": null,
            "scorecard": 1,
            "updated": "2021-01-03T10:13:06.644364-08:00"
        },
        "model": "colleges.FieldOfStudy",
        "pk": 1
    },
    {
        "fields": {
            "cip_code": "1901",
            "cip_title": "Family and Consumer Sciences/Human Sciences, General.",
            "college": 1,
            "created": "2021-01-03T10:13:06.644364-08:00",
            "credential_level": "Bachelor’s Degree",
            "credential_title": "Bachelors Degree",
            "debt_meam": 38241,
            "debt_median": 43000,
            "debt_monthly_payment": 410,
            "debt_num_students": null,
            "earnings_1yr_median_earnings": null,
            "earnings_1yr_not_working_not_enrolled_num_students": null,
            "earnings_1yr_over_poverty_line_num_students": null,
            "earnings_1yr_working_not_enrolled_num_students": null,
            "earnings_2yr_median_earnings": null,
            "earnings_2yr_not_working_not_enrolled_num_students": null,
            "earnings_2yr_over_poverty_line_num_students": null,
            "earnings_2yr_working_not_enrolled_num_students": null,
            "ipeds_awards1_num_students": 9,
            "ipeds_awards2_num_students": 20,
            "plus_debt_mean": null,
            "plus_debt_median": null,
            "plus_debt_monthly_payment": null,
            "plus_debt_num_students": null,
            "scorecard": 1,
            "updated": "2021-01-03T10:13:06.644364-08:00"
        },
        "model": "colleges.FieldOfStudy",
        "pk": 1
    },
    {
        "fields": {
            "cip_code": "1901",
            "cip_title": "Family and Consumer Sciences/Human Sciences, General.",
            "college": 1,
            "created": "2021-01-03T10:13:06.644364-08:00",
            "credential_level": "Master's Degree",
            "credential_title": "Master's Degree",
            "debt_meam": null,
            "debt_median": null,
            "debt_monthly_payment": null,
            "debt_num_students": null,
            "earnings_1yr_median_earnings": 37208,
            "earnings_1yr_not_working_not_enrolled_num_students": 2,
            "earnings_1yr_over_poverty_line_num_students": 10,
            "earnings_1yr_working_not_enrolled_num_students": 11,
            "earnings_2yr_median_earnings": null,
            "earnings_2yr_not_working_not_enrolled_num_students": null,
            "earnings_2yr_over_poverty_line_num_students": null,
            "earnings_2yr_working_not_enrolled_num_students": null,
            "ipeds_awards1_num_students": 8,
            "ipeds_awards2_num_students": 10,
            "plus_debt_mean": null,
            "plus_debt_median": null,
            "plus_debt_monthly_payment": null,
            "plus_debt_num_students": null,
            "scorecard": 1,
            "updated": "2021-01-03T10:13:06.644364-08:00"
        },
        "model": "colleges.FieldOfStudy",
        "pk": 1
    },
    {
        "fields": {
            "cip_code": "2301",
            "cip_title": "English Language and Literature, General.",
            "college": 1,
            "created": "2021-01-03T10:13:06.644364-08:00",
            "credential_level": "Bachelor’s Degree",
            "credential_title": "Bachelors Degree",
            "debt_meam": null,
            "debt_median": null,
            "debt_monthly_payment": null,
            "debt_num_students": null,
            "earnings_1yr_median_earnings": null,
            "earnings_1yr_not_working_not_enrolled_num_students": null,
            "earnings_1yr_over_poverty_line_num_students": null,
            "earnings_1yr_working_not_enrolled_num_students": null,
            "earnings_2yr_median_earnings": null,
            "earnings_2yr_not_working_not_enrolled_num_students": null,
            "earnings_2yr_over_poverty_line_num_students": null,
            "earnings_2yr_working_not_enrolled_num_students": null,
            "ipeds_awards1_num_students": 6,
            "ipeds_awards2_num_students": 8,
            "plus_debt_mean": null,
            "plus_debt_median": null,
            "plus_debt_monthly_payment": null,
            "plus_debt_num_students": null,
            "scorecard": 1,
            "updated": "2021-01-03T10:13:06.644364-08:00"
        },
        "model": "colleges.FieldOfStudy",
        "pk": 1
    },
    {
        "fields": {
            "cip_code": "2401",
            "cip_title": "Liberal Arts and Sciences, General Studies and Humanities.",
            "college": 1,
            "created": "2021-01-03T10:13:06.644364-08:00",
            "credential_level": "Bachelor’s Degree",
            "credential_title": "Bachelors Degree",
            "debt_meam": null,
            "debt_median": 39000,
            "debt_monthly_payment": 372,
            "debt_num_students": 28,
            "earnings_1yr_median_earnings": 26519,
            "earnings_1yr_not_working_not_enrolled_num_students": 1,
            "earnings_1yr_over_poverty_line_num_students": 21,
            "earnings_1yr_working_not_enrolled_num_students": 25,
            "earnings_2yr_median_earnings": 24615,
            "earnings_2yr_not_working_not_enrolled_num_students": 0,
            "earnings_2yr_over_poverty_line_num_students": 21,
            "earnings_2yr_working_not_enrolled_num_students": 30,
            "ipeds_awards1_num_students": 28,
            "ipeds_awards2_num_students": 24,
            "plus_debt_mean": null,
            "plus_debt_median": null,
            "plus_debt_monthly_payment": null,
            "plus_debt_num_students": null,
            "scorecard": 1,
            "updated": "2021-01-03T10:13:06.644364-08:00"
        },
        "model": "colleges.FieldOfStudy",
        "pk": 1
    },
    {
        "fields": {
            "cip_code": "2601",
            "cip_title": "Biology, General.",
            "college": 1,
            "created": "2021-01-03T10:13:06.644364-08:00",
            "credential_level": "Bachelor’s Degree",
            "credential_title": "Bachelors Degree",
            "debt_meam": null,
            "debt_median": 34000,
            "debt_monthly_payment": 324,
            "debt_num_students": 74,
            "earnings_1yr_median_earnings": 23207,
            "earnings_1yr_not_working_not_enrolled_num_students": 1,
            "earnings_1yr_over_poverty_line_num_students": 21,
            "earnings_1yr_working_not_enrolled_num_students": 32,
            "earnings_2yr_median_earnings": 26353,
            "earnings_2yr_not_working_not_enrolled_num_students": 2,
            "earnings_2yr_over_poverty_line_num_students": 27,
            "earnings_2yr_working_not_enrolled_num_students": 32,
            "ipeds_awards1_num_students": 43,
            "ipeds_awards2_num_students": 47,
            "plus_debt_mean": null,
            "plus_debt_median": 19916,
            "plus_debt_monthly_payment": 214,
            "plus_debt_num_students": 33,
            "scorecard": 1,
            "updated": "2021-01-03T10:13:06.644364-08:00"
        },
        "model": "colleges.FieldOfStudy",
        "pk": 1
    },
    {
        "fields": {
            "cip_code": "2601",
            "cip_title": "Biology, General.",
            "college": 1,
            "created": "2021-01-03T10:13:06.644364-08:00",
            "credential_level": "Master's Degree",
            "credential_title": "Master's Degree",
            "debt_meam": null,
            "debt_median": null,
            "debt_monthly_payment": null,
            "debt_num_students": null,
            "earnings_1yr_median_earnings": 36132,
            "earnings_1yr_not_working_not_enrolled_num_students": 1,
            "earnings_1yr_over_poverty_line_num_students": 20,
            "earnings_1yr_working_not_enrolled_num_students": 22,
            "earnings_2yr_median_earnings": 35594,
            "earnings_2yr_not_working_not_enrolled_num_students": 1,
            "earnings_2yr_over_poverty_line_num_students": 20,
            "earnings_2yr_working_not_enrolled_num_students": 25,
            "ipeds_awards1_num_students": 23,
            "ipeds_awards2_num_students": 22,
            "plus_debt_mean": null,
            "plus_debt_median": null,
            "plus_debt_monthly_payment": null,
            "plus_debt_num_students": null,
            "scorecard": 1,
            "updated": "2021-01-03T10:13:06.644364-08:00"
        },
        "model": "colleges.FieldOfStudy",
        "pk": 1
    },
    {
        "fields": {
            "cip_code": "2701",
            "cip_title": "Mathematics.",
            "college": 1,
            "created": "2021-01-03T10:13:06.644364-08:00",
            "credential_level": "Bachelor’s Degree",
            "credential_title": "Bachelors Degree",
            "debt_meam": null,
            "debt_median": null,
            "debt_monthly_payment": null,
            "debt_num_students": null,
            "earnings_1yr_median_earnings": null,
            "earnings_1yr_not_working_not_enrolled_num_students": null,
            "earnings_1yr_over_poverty_line_num_students": null,
            "earnings_1yr_working_not_enrolled_num_students": null,
            "earnings_2yr_median_earnings": null,
            "earnings_2yr_not_working_not_enrolled_num_students": null,
            "earnings_2yr_over_poverty_line_num_students": null,
            "earnings_2yr_working_not_enrolled_num_students": null,
            "ipeds_awards1_num_students": 0,
            "ipeds_awards2_num_students": 3,
            "plus_debt_mean": null,
            "plus_debt_median": null,
            "plus_debt_monthly_payment": null,
            "plus_debt_num_students": null,
            "scorecard": 1,
            "updated": "2021-01-03T10:13:06.644364-08:00"
        },
        "model": "colleges.FieldOfStudy",
        "pk": 1
    },
    {
        "fields": {
            "cip_code": "3105",
            "cip_title": "Health and Physical Education/Fitness.",
            "college": 1,
            "created": "2021-01-03T10:13:06.644364-08:00",
            "credential_level": "Bachelor’s Degree",
            "credential_title": "Bachelors Degree",
            "debt_meam": null,
            "debt_median": null,
            "debt_monthly_payment": null,
            "debt_num_students": null,
            "earnings_1yr_median_earnings": null,
            "earnings_1yr_not_working_not_enrolled_num_students": null,
            "earnings_1yr_over_poverty_line_num_students": null,
            "earnings_1yr_working_not_enrolled_num_students": null,
            "earnings_2yr_median_earnings": null,
            "earnings_2yr_not_working_not_enrolled_num_students": null,
            "earnings_2yr_over_poverty_line_num_students": null,
            "earnings_2yr_working_not_enrolled_num_students": null,
            "ipeds_awards1_num_students": null,
            "ipeds_awards2_num_students": 1,
            "plus_debt_mean": null,
            "plus_debt_median": null,
            "plus_debt_monthly_payment": null,
            "plus_debt_num_students": null,
            "scorecard": 1,
            "updated": "2021-01-03T10:13:06.644364-08:00"
        },
        "model": "colleges.FieldOfStudy",
        "pk": 1
    },
    {
        "fields": {
            "cip_code": "3105",
            "cip_title": "Health and Physical Education/Fitness.",
            "college": 1,
            "created": "2021-01-03T10:13:06.644364-08:00",
            "credential_level": "Master's Degree",
            "credential_title": "Master's Degree",
            "debt_meam": null,
            "debt_median": null,
            "debt_monthly_payment": null,
            "debt_num_students": null,
            "earnings_1yr_median_earnings": 37568,
            "earnings_1yr_not_working_not_enrolled_num_students": 0,
            "earnings_1yr_over_poverty_line_num_students": 12,
            "earnings_1yr_working_not_enrolled_num_students": 12,
            "earnings_2yr_median_earnings": null,
            "earnings_2yr_not_working_not_enrolled_num_students": null,
            "earnings_2yr_over_poverty_line_num_students": null,
            "earnings_2yr_working_not_enrolled_num_students": null,
            "ipeds_awards1_num_students": 11,
            "ipeds_awards2_num_students": 12,
            "plus_debt_mean": null,
            "plus_debt_median": null,
            "plus_debt_monthly_payment": null,
            "plus_debt_num_students": null,
            "scorecard": 1,
            "updated": "2021-01-03T10:13:06.644364-08:00"
        },
        "model": "colleges.FieldOfStudy",
        "pk": 1
    },
    {
        "fields": {
            "cip_code": "4005",
            "cip_title": "Chemistry.",
            "college": 1,
            "created": "2021-01-03T10:13:06.644364-08:00",
            "credential_level": "Bachelor’s Degree",
            "credential_title": "Bachelors Degree",
            "debt_meam": null,
            "debt_median": 28500,
            "debt_monthly_payment": 272,
            "debt_num_students": null,
            "earnings_1yr_median_earnings": null,
            "earnings_1yr_not_working_not_enrolled_num_students": null,
            "earnings_1yr_over_poverty_line_num_students": null,
            "earnings_1yr_working_not_enrolled_num_students": null,
            "earnings_2yr_median_earnings": null,
            "earnings_2yr_not_working_not_enrolled_num_students": null,
            "earnings_2yr_over_poverty_line_num_students": null,
            "earnings_2yr_working_not_enrolled_num_students": null,
            "ipeds_awards1_num_students": 10,
            "ipeds_awards2_num_students": 14,
            "plus_debt_mean": 40451,
            "plus_debt_median": null,
            "plus_debt_monthly_payment": null,
            "plus_debt_num_students": null,
            "scorecard": 1,
            "updated": "2021-01-03T10:13:06.644364-08:00"
        },
        "model": "colleges.FieldOfStudy",
        "pk": 1
    },
    {
        "fields": {
            "cip_code": "4008",
            "cip_title": "Physics.",
            "college": 1,
            "created": "2021-01-03T10:13:06.644364-08:00",
            "credential_level": "Bachelor’s Degree",
            "credential_title": "Bachelors Degree",
            "debt_meam": null,
            "debt_median": null,
            "debt_monthly_payment": null,
            "debt_num_students": null,
            "earnings_1yr_median_earnings": null,
            "earnings_1yr_not_working_not_enrolled_num_students": null,
            "earnings_1yr_over_poverty_line_num_students": null,
            "earnings_1yr_working_not_enrolled_num_students": null,
            "earnings_2yr_median_earnings": null,
            "earnings_2yr_not_working_not_enrolled_num_students": null,
            "earnings_2yr_over_poverty_line_num_students": null,
            "earnings_2yr_working_not_enrolled_num_students": null,
            "ipeds_awards1_num_students": 6,
            "ipeds_awards2_num_students": 4,
            "plus_debt_mean": null,
            "plus_debt_median": null,
            "plus_debt_monthly_payment": null,
            "plus_debt_num_students": null,
            "scorecard": 1,
            "updated": "2021-01-03T10:13:06.644364-08:00"
        },
        "model": "colleges.FieldOfStudy",
        "pk": 1
    },
    {
        "fields": {
            "cip_code": "4008",
            "cip_title": "Physics.",
            "college": 1,
            "created": "2021-01-03T10:13:06.644364-08:00",
            "credential_level": "Master's Degree",
            "credential_title": "Master's Degree",
            "debt_meam": null,
            "debt_median": null,
            "debt_monthly_payment": null,
            "debt_num_students": null,
            "earnings_1yr_median_earnings": null,
            "earnings_1yr_not_working_not_enrolled_num_students": null,
            "earnings_1yr_over_poverty_line_num_students": null,
            "earnings_1yr_working_not_enrolled_num_students": null,
            "earnings_2yr_median_earnings": null,
            "earnings_2yr_not_working_not_enrolled_num_students": null,
            "earnings_2yr_over_poverty_line_num_students": null,
            "earnings_2yr_working_not_enrolled_num_students": null,
            "ipeds_awards1_num_students": 2,
            "ipeds_awards2_num_students": 3,
            "plus_debt_mean": null,
            "plus_debt_median": null,
            "plus_debt_monthly_payment": null,
            "plus_debt_num_students": null,
            "scorecard": 1,
            "updated": "2021-01-03T10:13:06.644364-08:00"
        },
        "model": "colleges.FieldOfStudy",
        "pk": 1
    },
    {
        "fields": {
            "cip_code": "4008",
            "cip_title": "Physics.",
            "college": 1,
            "created": "2021-01-03T10:13:06.644364-08:00",
            "credential_level": "Doctoral Degree",
            "credential_title": "Doctoral Degree",
            "debt_meam": null,
            "debt_median": null,
            "debt_monthly_payment": null,
            "debt_num_students": null,
            "earnings_1yr_median_earnings": null,
            "earnings_1yr_not_working_not_enrolled_num_students": null,
            "earnings_1yr_over_poverty_line_num_students": null,
            "earnings_1yr_working_not_enrolled_num_students": null,
            "earnings_2yr_median_earnings": null,
            "earnings_2yr_not_working_not_enrolled_num_students": null,
            "earnings_2yr_over_poverty_line_num_students": null,
            "earnings_2yr_working_not_enrolled_num_students": null,
            "ipeds_awards1_num_students": 3,
            "ipeds_awards2_num_students": null,
            "plus_debt_mean": null,
            "plus_debt_median": null,
            "plus_debt_monthly_payment": null,
            "plus_debt_num_students": null,
            "scorecard": 1,
            "updated": "2021-01-03T10:13:06.644364-08:00"
        },
        "model": "colleges.FieldOfStudy",
        "pk": 1
    },
    {
        "fields": {
            "cip_code": "4201",
            "cip_title": "Psychology, General.",
            "college": 1,
            "created": "2021-01-03T10:13:06.644364-08:00",
            "credential_level": "Bachelor’s Degree",
            "credential_title": "Bachelors Degree",
            "debt_meam": null,
            "debt_median": 34000,
            "debt_monthly_payment": 324,
            "debt_num_students": 49,
            "earnings_1yr_median_earnings": 24615,
            "earnings_1yr_not_working_not_enrolled_num_students": 1,
            "earnings_1yr_over_poverty_line_num_students": 15,
            "earnings_1yr_working_not_enrolled_num_students": 22,
            "earnings_2yr_median_earnings": 19227,
            "earnings_2yr_not_working_not_enrolled_num_students": 1,
            "earnings_2yr_over_poverty_line_num_students": 5,
            "earnings_2yr_working_not_enrolled_num_students": 11,
            "ipeds_awards1_num_students": 26,
            "ipeds_awards2_num_students": 32,
            "plus_debt_mean": null,
            "plus_debt_median": 20954,
            "plus_debt_monthly_payment": 225,
            "plus_debt_num_students": 28,
            "scorecard": 1,
            "updated": "2021-01-03T10:13:06.644364-08:00"
        },
        "model": "colleges.FieldOfStudy",
        "pk": 1
    },
    {
        "fields": {
            "cip_code": "4228",
            "cip_title": "Clinical, Counseling and Applied Psychology.",
            "college": 1,
            "created": "2021-01-03T10:13:06.644364-08:00",
            "credential_level": "Master's Degree",
            "credential_title": "Master's Degree",
            "debt_meam": null,
            "debt_median": null,
            "debt_monthly_payment": null,
            "debt_num_students": null,
            "earnings_1yr_median_earnings": 33535,
            "earnings_1yr_not_working_not_enrolled_num_students": 5,
            "earnings_1yr_over_poverty_line_num_students": 54,
            "earnings_1yr_working_not_enrolled_num_students": 64,
            "earnings_2yr_median_earnings": 34793,
            "earnings_2yr_not_working_not_enrolled_num_students": 1,
            "earnings_2yr_over_poverty_line_num_students": 53,
            "earnings_2yr_working_not_enrolled_num_students": 60,
            "ipeds_awards1_num_students": 56,
            "ipeds_awards2_num_students": 54,
            "plus_debt_mean": null,
            "plus_debt_median": null,
            "plus_debt_monthly_payment": null,
            "plus_debt_num_students": null,
            "scorecard": 1,
            "updated": "2021-01-03T10:13:06.644364-08:00"
        },
        "model": "colleges.FieldOfStudy",
        "pk": 1
    },
    {
        "fields": {
            "cip_code": "4301",
            "cip_title": "Criminal Justice and Corrections.",
            "college": 1,
            "created": "2021-01-03T10:13:06.644364-08:00",
            "credential_level": "Bachelor’s Degree",
            "credential_title": "Bachelors Degree",
            "debt_meam": null,
            "debt_median": 39000,
            "debt_monthly_payment": 372,
            "debt_num_students": 48,
            "earnings_1yr_median_earnings": 24267,
            "earnings_1yr_not_working_not_enrolled_num_students": 0,
            "earnings_1yr_over_poverty_line_num_students": 20,
            "earnings_1yr_working_not_enrolled_num_students": 29,
            "earnings_2yr_median_earnings": null,
            "earnings_2yr_not_working_not_enrolled_num_students": null,
            "earnings_2yr_over_poverty_line_num_students": null,
            "earnings_2yr_working_not_enrolled_num_students": null,
            "ipeds_awards1_num_students": 25,
            "ipeds_awards2_num_students": 29,
            "plus_debt_mean": null,
            "plus_debt_median": 21628,
            "plus_debt_monthly_payment": 233,
            "plus_debt_num_students": 23,
            "scorecard": 1,
            "updated": "2021-01-03T10:13:06.644364-08:00"
        },
        "model": "colleges.FieldOfStudy",
        "pk": 1
    },
    {
        "fields": {
            "cip_code": "4407",
            "cip_title": "Social Work.",
            "college": 1,
            "created": "2021-01-03T10:13:06.644364-08:00",
            "credential_level": "Bachelor’s Degree",
            "credential_title": "Bachelors Degree",
            "debt_meam": null,
            "debt_median": 42020,
            "debt_monthly_payment": 401,
            "debt_num_students": 55,
            "earnings_1yr_median_earnings": 25194,
            "earnings_1yr_not_working_not_enrolled_num_students": 1,
            "earnings_1yr_over_poverty_line_num_students": 10,
            "earnings_1yr_working_not_enrolled_num_students": 12,
            "earnings_2yr_median_earnings": null,
            "earnings_2yr_not_working_not_enrolled_num_students": null,
            "earnings_2yr_over_poverty_line_num_students": null,
            "earnings_2yr_working_not_enrolled_num_students": null,
            "ipeds_awards1_num_students": 34,
            "ipeds_awards2_num_students": 25,
            "plus_debt_mean": null,
            "plus_debt_median": null,
            "plus_debt_monthly_payment": null,
            "plus_debt_num_students": 18,
            "scorecard": 1,
            "updated": "2021-01-03T10:13:06.644364-08:00"
        },
        "model": "colleges.FieldOfStudy",
        "pk": 1
    },
    {
        "fields": {
            "cip_code": "4407",
            "cip_title": "Social Work.",
            "college": 1,
            "created": "2021-01-03T10:13:06.644364-08:00",
            "credential_level": "Master's Degree",
            "credential_title": "Master's Degree",
            "debt_meam": null,
            "debt_median": null,
            "debt_monthly_payment": null,
            "debt_num_students": null,
            "earnings_1yr_median_earnings": 38065,
            "earnings_1yr_not_working_not_enrolled_num_students": 3,
            "earnings_1yr_over_poverty_line_num_students": 132,
            "earnings_1yr_working_not_enrolled_num_students": 138,
            "earnings_2yr_median_earnings": 37819,
            "earnings_2yr_not_working_not_enrolled_num_students": 1,
            "earnings_2yr_over_poverty_line_num_students": 82,
            "earnings_2yr_working_not_enrolled_num_students": 83,
            "ipeds_awards1_num_students": 92,
            "ipeds_awards2_num_students": 79,
            "plus_debt_mean": null,
            "plus_debt_median": null,
            "plus_debt_monthly_payment": null,
            "plus_debt_num_students": null,
            "scorecard": 1,
            "updated": "2021-01-03T10:13:06.644364-08:00"
        },
        "model": "colleges.FieldOfStudy",
        "pk": 1
    },
    {
        "fields": {
            "cip_code": "4510",
            "cip_title": "Political Science and Government.",
            "college": 1,
            "created": "2021-01-03T10:13:06.644364-08:00",
            "credential_level": "Bachelor’s Degree",
            "credential_title": "Bachelors Degree",
            "debt_meam": null,
            "debt_median": null,
            "debt_monthly_payment": null,
            "debt_num_students": null,
            "earnings_1yr_median_earnings": null,
            "earnings_1yr_not_working_not_enrolled_num_students": null,
            "earnings_1yr_over_poverty_line_num_students": null,
            "earnings_1yr_working_not_enrolled_num_students": null,
            "earnings_2yr_median_earnings": null,
            "earnings_2yr_not_working_not_enrolled_num_students": null,
            "earnings_2yr_over_poverty_line_num_students": null,
            "earnings_2yr_working_not_enrolled_num_students": null,
            "ipeds_awards1_num_students": 5,
            "ipeds_awards2_num_students": 11,
            "plus_debt_mean": null,
            "plus_debt_median": null,
            "plus_debt_monthly_payment": null,
            "plus_debt_num_students": null,
            "scorecard": 1,
            "updated": "2021-01-03T10:13:06.644364-08:00"
        },
        "model": "colleges.FieldOfStudy",
        "pk": 1
    },
    {
        "fields": {
            "cip_code": "4511",
            "cip_title": "Sociology.",
            "college": 1,
            "created": "2021-01-03T10:13:06.644364-08:00",
            "credential_level": "Bachelor’s Degree",
            "credential_title": "Bachelors Degree",
            "debt_meam": null,
            "debt_median": null,
            "debt_monthly_payment": null,
            "debt_num_students": null,
            "earnings_1yr_median_earnings": null,
            "earnings_1yr_not_working_not_enrolled_num_students": null,
            "earnings_1yr_over_poverty_line_num_students": null,
            "earnings_1yr_working_not_enrolled_num_students": null,
            "earnings_2yr_median_earnings": null,
            "earnings_2yr_not_working_not_enrolled_num_students": null,
            "earnings_2yr_over_poverty_line_num_students": null,
            "earnings_2yr_working_not_enrolled_num_students": null,
            "ipeds_awards1_num_students": 6,
            "ipeds_awards2_num_students": 7,
            "plus_debt_mean": null,
            "plus_debt_median": null,
            "plus_debt_monthly_payment": null,
            "plus_debt_num_students": null,
            "scorecard": 1,
            "updated": "2021-01-03T10:13:06.644364-08:00"
        },
        "model": "colleges.FieldOfStudy",
        "pk": 1
    },
    {
        "fields": {
            "cip_code": "5007",
            "cip_title": "Fine and Studio Arts.",
            "college": 1,
            "created": "2021-01-03T10:13:06.644364-08:00",
            "credential_level": "Bachelor’s Degree",
            "credential_title": "Bachelors Degree",
            "debt_meam": null,
            "debt_median": null,
            "debt_monthly_payment": null,
            "debt_num_students": null,
            "earnings_1yr_median_earnings": null,
            "earnings_1yr_not_working_not_enrolled_num_students": null,
            "earnings_1yr_over_poverty_line_num_students": null,
            "earnings_1yr_working_not_enrolled_num_students": null,
            "earnings_2yr_median_earnings": null,
            "earnings_2yr_not_working_not_enrolled_num_students": null,
            "earnings_2yr_over_poverty_line_num_students": null,
            "earnings_2yr_working_not_enrolled_num_students": null,
            "ipeds_awards1_num_students": 6,
            "ipeds_awards2_num_students": 6,
            "plus_debt_mean": null,
            "plus_debt_median": null,
            "plus_debt_monthly_payment": null,
            "plus_debt_num_students": null,
            "scorecard": 1,
            "updated": "2021-01-03T10:13:06.644364-08:00"
        },
        "model": "colleges.FieldOfStudy",
        "pk": 1
    },
    {
        "fields": {
            "cip_code": "5009",
            "cip_title": "Music.",
            "college": 1,
            "created": "2021-01-03T10:13:06.644364-08:00",
            "credential_level": "Bachelor’s Degree",
            "credential_title": "Bachelors Degree",
            "debt_meam": null,
            "debt_median": null,
            "debt_monthly_payment": null,
            "debt_num_students": null,
            "earnings_1yr_median_earnings": null,
            "earnings_1yr_not_working_not_enrolled_num_students": null,
            "earnings_1yr_over_poverty_line_num_students": null,
            "earnings_1yr_working_not_enrolled_num_students": null,
            "earnings_2yr_median_earnings": null,
            "earnings_2yr_not_working_not_enrolled_num_students": null,
            "earnings_2yr_over_poverty_line_num_students": null,
            "earnings_2yr_working_not_enrolled_num_students": null,
            "ipeds_awards1_num_students": 6,
            "ipeds_awards2_num_students": 6,
            "plus_debt_mean": null,
            "plus_debt_median": null,
            "plus_debt_monthly_payment": null,
            "plus_debt_num_students": null,
            "scorecard": 1,
            "updated": "2021-01-03T10:13:06.644364-08:00"
        },
        "model": "colleges.FieldOfStudy",
        "pk": 1
    },
    {
        "fields": {
            "cip_code": "5102",
            "cip_title": "Communication Disorders Sciences and Services.",
            "college": 1,
            "created": "2021-01-03T10:13:06.644364-08:00",
            "credential_level": "Master's Degree",
            "credential_title": "Master's Degree",
            "debt_meam": null,
            "debt_median": null,
            "debt_monthly_payment": null,
            "debt_num_students": null,
            "earnings_1yr_median_earnings": 50439,
            "earnings_1yr_not_working_not_enrolled_num_students": 1,
            "earnings_1yr_over_poverty_line_num_students": 33,
            "earnings_1yr_working_not_enrolled_num_students": 33,
            "earnings_2yr_median_earnings": 55036,
            "earnings_2yr_not_working_not_enrolled_num_students": 1,
            "earnings_2yr_over_poverty_line_num_students": 36,
            "earnings_2yr_working_not_enrolled_num_students": 36,
            "ipeds_awards1_num_students": 28,
            "ipeds_awards2_num_students": 28,
            "plus_debt_mean": null,
            "plus_debt_median": null,
            "plus_debt_monthly_payment": null,
            "plus_debt_num_students": null,
            "scorecard": 1,
            "updated": "2021-01-03T10:13:06.644364-08:00"
        },
        "model": "colleges.FieldOfStudy",
        "pk": 1
    },
    {
        "fields": {
            "cip_code": "5202",
            "cip_title": "Business Administration, Management and Operations.",
            "college": 1,
            "created": "2021-01-03T10:13:06.644364-08:00",
            "credential_level": "Bachelor’s Degree",
            "credential_title": "Bachelors Degree",
            "debt_meam": null,
            "debt_median": 37500,
            "debt_monthly_payment": 358,
            "debt_num_students": 64,
            "earnings_1yr_median_earnings": 41087,
            "earnings_1yr_not_working_not_enrolled_num_students": 2,
            "earnings_1yr_over_poverty_line_num_students": 48,
            "earnings_1yr_working_not_enrolled_num_students": 55,
            "earnings_2yr_median_earnings": 39153,
            "earnings_2yr_not_working_not_enrolled_num_students": 2,
            "earnings_2yr_over_poverty_line_num_students": 49,
            "earnings_2yr_working_not_enrolled_num_students": 53,
            "ipeds_awards1_num_students": 39,
            "ipeds_awards2_num_students": 42,
            "plus_debt_mean": 22721,
            "plus_debt_median": 13928,
            "plus_debt_monthly_payment": 150,
            "plus_debt_num_students": 27,
            "scorecard": 1,
            "updated": "2021-01-03T10:13:06.644364-08:00"
        },
        "model": "colleges.FieldOfStudy",
        "pk": 1
    },
    {
        "fields": {
            "cip_code": "5202",
            "cip_title": "Business Administration, Management and Operations.",
            "college": 1,
            "created": "2021-01-03T10:13:06.644364-08:00",
            "credential_level": "Master's Degree",
            "credential_title": "Master's Degree",
            "debt_meam": null,
            "debt_median": null,
            "debt_monthly_payment": null,
            "debt_num_students": null,
            "earnings_1yr_median_earnings": 40737,
            "earnings_1yr_not_working_not_enrolled_num_students": 3,
            "earnings_1yr_over_poverty_line_num_students": 41,
            "earnings_1yr_working_not_enrolled_num_students": 45,
            "earnings_2yr_median_earnings": 43798,
            "earnings_2yr_not_working_not_enrolled_num_students": 1,
            "earnings_2yr_over_poverty_line_num_students": 34,
            "earnings_2yr_working_not_enrolled_num_students": 37,
            "ipeds_awards1_num_students": 30,
            "ipeds_awards2_num_students": 27,
            "plus_debt_mean": null,
            "plus_debt_median": null,
            "plus_debt_monthly_payment": null,
            "plus_debt_num_students": null,
            "scorecard": 1,
            "updated": "2021-01-03T10:13:06.644364-08:00"
        },
        "model": "colleges.FieldOfStudy",
        "pk": 1
    },
    {
        "fields": {
            "cip_code": "5203",
            "cip_title": "Accounting and Related Services.",
            "college": 1,
            "created": "2021-01-03T10:13:06.644364-08:00",
            "credential_level": "Bachelor’s Degree",
            "credential_title": "Bachelors Degree",
            "debt_meam": null,
            "debt_median": 34278,
            "debt_monthly_payment": 327,
            "debt_num_students": 34,
            "earnings_1yr_median_earnings": 39909,
            "earnings_1yr_not_working_not_enrolled_num_students": 0,
            "earnings_1yr_over_poverty_line_num_students": 21,
            "earnings_1yr_working_not_enrolled_num_students": 23,
            "earnings_2yr_median_earnings": 35416,
            "earnings_2yr_not_working_not_enrolled_num_students": 0,
            "earnings_2yr_over_poverty_line_num_students": 10,
            "earnings_2yr_working_not_enrolled_num_students": 12,
            "ipeds_awards1_num_students": 17,
            "ipeds_awards2_num_students": 25,
            "plus_debt_mean": null,
            "plus_debt_median": null,
            "plus_debt_monthly_payment": null,
            "plus_debt_num_students": 14,
            "scorecard": 1,
            "updated": "2021-01-03T10:13:06.644364-08:00"
        },
        "model": "colleges.FieldOfStudy",
        "pk": 1
    },
    {
        "fields": {
            "cip_code": "5208",
            "cip_title": "Finance and Financial Management Services.",
            "college": 1,
            "created": "2021-01-03T10:13:06.644364-08:00",
            "credential_level": "Bachelor’s Degree",
            "credential_title": "Bachelors Degree",
            "debt_meam": 30463,
            "debt_median": null,
            "debt_monthly_payment": null,
            "debt_num_students": null,
            "earnings_1yr_median_earnings": 35060,
            "earnings_1yr_not_working_not_enrolled_num_students": 1,
            "earnings_1yr_over_poverty_line_num_students": 12,
            "earnings_1yr_working_not_enrolled_num_students": 13,
            "earnings_2yr_median_earnings": 37568,
            "earnings_2yr_not_working_not_enrolled_num_students": 0,
            "earnings_2yr_over_poverty_line_num_students": 19,
            "earnings_2yr_working_not_enrolled_num_students": 21,
            "ipeds_awards1_num_students": 8,
            "ipeds_awards2_num_students": 5,
            "plus_debt_mean": null,
            "plus_debt_median": null,
            "plus_debt_monthly_payment": null,
            "plus_debt_num_students": null,
            "scorecard": 1,
            "updated": "2021-01-03T10:13:06.644364-08:00"
        },
        "model": "colleges.FieldOfStudy",
        "pk": 1
    },
    {
        "fields": {
            "cip_code": "5214",
            "cip_title": "Marketing.",
            "college": 1,
            "created": "2021-01-03T10:13:06.644364-08:00",
            "credential_level": "Bachelor’s Degree",
            "credential_title": "Bachelors Degree",
            "debt_meam": null,
            "debt_median": null,
            "debt_monthly_payment": null,
            "debt_num_students": null,
            "earnings_1yr_median_earnings": null,
            "earnings_1yr_not_working_not_enrolled_num_students": null,
            "earnings_1yr_over_poverty_line_num_students": null,
            "earnings_1yr_working_not_enrolled_num_students": null,
            "earnings_2yr_median_earnings": null,
            "earnings_2yr_not_working_not_enrolled_num_students": null,
            "earnings_2yr_over_poverty_line_num_students": null,
            "earnings_2yr_working_not_enrolled_num_students": null,
            "ipeds_awards1_num_students": 13,
            "ipeds_awards2_num_students": 8,
            "plus_debt_mean": null,
            "plus_debt_median": null,
            "plus_debt_monthly_payment": null,
            "plus_debt_num_students": null,
            "scorecard": 1,
            "updated": "2021-01-03T10:13:06.644364-08:00"
        },
        "model": "colleges.FieldOfStudy",
        "pk": 1
    }
]