[
{
  "model": "colleges.collegestatus",
  "pk": 1,
  "fields": {
    "user": 10,
    "college": 876,
    "status": "accepted",
    "award_status": "emailed user",
    "in_state_tuition": "yes",
    "net_price": null,
    "residency": "oncampus",
    "award_costs_missing": false,
    "award_total_costs": 51420,
    "award_total_grants": 35060,
    "award_net_price": 16360,
    "most_affordable": false,
    "family": 0,
    "job": 0,
    "other_scholarships": 0,
    "savings": 0,
    "work_study": 1500,
    "loan_plus": 0,
    "loan_private": 0,
    "loan_school": 0,
    "loan_subsidized": 2500,
    "loan_unsubsidized": 0,
    "created": "2021-02-17T11:46:08.222",
    "updated": "2021-03-01T10:40:58.540"
  }
},
{
  "model": "colleges.collegestatus",
  "pk": 2,
  "fields": {
    "user": 10,
    "college": 3705,
    "status": "accepted",
    "award_status": "emailed user",
    "in_state_tuition": "yes",
    "net_price": null,
    "residency": "oncampus",
    "award_costs_missing": false,
    "award_total_costs": 48900,
    "award_total_grants": 15566,
    "award_net_price": 33334,
    "most_affordable": false,
    "family": null,
    "job": null,
    "other_scholarships": null,
    "savings": null,
    "work_study": null,
    "loan_plus": null,
    "loan_private": null,
    "loan_school": null,
    "loan_subsidized": null,
    "loan_unsubsidized": null,
    "created": "2021-02-17T11:46:28.562",
    "updated": "2021-03-01T10:40:56.829"
  }
}
]
